figures/__init__.py
figures/admin.py
figures/apps.py
figures/compat.py
figures/course.py
figures/enrollment.py
figures/filters.py
figures/helpers.py
figures/log.py
figures/mau.py
figures/metrics.py
figures/models.py
figures/pagination.py
figures/permissions.py
figures/progress.py
figures/query.py
figures/serializers.py
figures/sites.py
figures/tasks.py
figures/urls.py
figures/views.py
figures/management/__init__.py
figures/management/base.py
figures/management/commands/__init__.py
figures/management/commands/backfill_figures_daily_metrics.py
figures/management/commands/backfill_figures_enrollment_data.py
figures/management/commands/backfill_figures_metrics.py
figures/management/commands/backfill_figures_monthly_metrics.py
figures/management/commands/populate_figures_metrics.py
figures/management/commands/repair_figures_backfilled_progress.py
figures/management/commands/run_figures_mau_metrics.py
figures/management/commands/run_figures_monthly_metrics.py
figures/migrations/0001_initial.py
figures/migrations/0002_course_daily_metrics.py
figures/migrations/0003_pipelineerror.py
figures/migrations/0004_learner_course_grade_metrics.py
figures/migrations/0005_add_site_to_models.py
figures/migrations/0006_remove_default_site_from_models.py
figures/migrations/0007_modify_course_daily_metrics.py
figures/migrations/0008_cdm_meta_update.py
figures/migrations/0009_mau_metrics.py
figures/migrations/0010_site_monthly_metrics.py
figures/migrations/0011_add_mau_to_site_daily_metrics.py
figures/migrations/0012_alter_pipelineerror_field.py
figures/migrations/0013_add_indexes_to_lcgm_date_for_and_course_id.py
figures/migrations/0014_add_indexes_to_daily_metrics.py
figures/migrations/0015_add_enrollment_data_model.py
figures/migrations/0016_add_collect_elapsed_to_ed_and_lcgm.py
figures/migrations/0017_add_monthly_active_enrollment_model.py
figures/migrations/__init__.py
figures/pipeline/__init__.py
figures/pipeline/backfill.py
figures/pipeline/course_daily_metrics.py
Figures-0.4.4.dist-info/LICENSE
Figures-0.4.4.dist-info/METADATA
Figures-0.4.4.dist-info/WHEEL
Figures-0.4.4.dist-info/entry_points.txt
Figures-0.4.4.dist-info/top_level.txt
Figures-0.4.4.dist-info/RECORD
